pymaf/__init__.py
pymaf/maf.py
pymaf-0.3.1.dist-info/WHEEL
pymaf-0.3.1.dist-info/METADATA
pymaf-0.3.1.dist-info/RECORD
